<ConfigurationGroup>
	<title>Categories Pages</title>
	<key>categoriesPages</key>
	<description>Configuration Settings For The Categories Pages Extension to allow multiple categories on a specific page</description>
	<tabs>
		<general>
			<title>General</title>
			<description>General Extension Settings</description>
			<configurations>
				<EXTENSION_CATEGORIES_PAGES_INSTALLED editable="false">
					<title>Installation Status</title>
					<value>False</value>
					<description></description>
				</EXTENSION_CATEGORIES_PAGES_INSTALLED>
				<EXTENSION_CATEGORIES_PAGES_ENABLED>
					<title>Enable Categories Pages</title>
					<value>True</value>
					<description>Enable Or Disable The Categories Pages Extension</description>
					<set_function>
						<type>radio</type>
						<values>
							<value>True</value>
							<value>False</value>
						</values>
					</set_function>
				</EXTENSION_CATEGORIES_PAGES_ENABLED>
			</configurations>
		</general>
	</tabs>
</ConfigurationGroup>